<?xml version = '1.0' encoding = 'UTF-8'?>
<Relation class="oracle.dbtools.crest.model.design.logical.Relation" name="Relation_137" directorySegmentName="seg_1" id="414985D5-F1F9-551C-32C7-969A734B892C">
<createdBy>Macias</createdBy>
<createdTime>2021-07-14 02:36:04 UTC</createdTime>
<ownerDesignName>MODELO</ownerDesignName>
<engineerTo>
<item key="2BF282FF-0E63-5EE6-885A-E0D1EF18FFC3" value="true"/>
</engineerTo>
<sourcePk>BEB7AD2A-5A38-91B0-C30C-0103FCDA7B2C</sourcePk>
<identifying>false</identifying>
<nameOnSource>CABHOMOL</nameOnSource>
<nameOnTarget>ALUMNO</nameOnTarget>
<optionalSource>true</optionalSource>
<optionalTarget>false</optionalTarget>
<sourceCardinality>1</sourceCardinality>
<sourceEntity>1069FF90-6A14-3C49-EFF0-2274EBB80A10</sourceEntity>
<targetCardinalityString>*</targetCardinalityString>
<targetEntity>C705D216-7942-CFD7-D5B9-651A2A9CB83F</targetEntity>
<transferable>true</transferable>
<deleteRule>NO ACTION</deleteRule>
</Relation>
